fiber/__init__.py
fiber/backend.py
fiber/cli.py
fiber/config.py
fiber/context.py
fiber/core.py
fiber/docker_backend.py
fiber/init.py
fiber/kubernetes_backend.py
fiber/local_backend.py
fiber/managers.py
fiber/meta.py
fiber/pool.py
fiber/popen_fiber_spawn.py
fiber/process.py
fiber/queues.py
fiber/socket.py
fiber/spawn.py
fiber/util.py
fiber/experimental/__init__.py
fiber/experimental/ring.py
tests/__init__.py
tests/test_backend.py
tests/test_config.py
tests/test_docker_backend.py
tests/test_managers.py
tests/test_misc.py
tests/test_pool.py
tests/test_popen.py
tests/test_process.py
tests/test_process_misc.py
tests/test_queue.py
traxfiber-0.0.14.dist-info/LICENSE
traxfiber-0.0.14.dist-info/METADATA
traxfiber-0.0.14.dist-info/WHEEL
traxfiber-0.0.14.dist-info/entry_points.txt
traxfiber-0.0.14.dist-info/top_level.txt
traxfiber-0.0.14.dist-info/RECORD
