Metadata-Version: 2.1
Name: traxfiber
Version: 0.0.14
Summary: A distributed computing library for modern computer clusters
Home-page: https://github.com/trax-retail/trax-fiber
Author: Jiale Zhi
Author-email: jiale@uber.com
License: Apache 2.0
Platform: UNKNOWN
Classifier: License :: OSI Approved :: Apache Software License
Classifier: Programming Language :: Python :: 3
Classifier: Topic :: System :: Distributed Computing
Requires-Dist: nnpy-bundle
Requires-Dist: psutil
Requires-Dist: docker (<=4.2.2)
Requires-Dist: cloudpickle
Requires-Dist: kubernetes
Requires-Dist: requests
Requires-Dist: click
Provides-Extra: test
Requires-Dist: pytest ; extra == 'test'
Requires-Dist: docker (<=4.2.2) ; extra == 'test'
Requires-Dist: flake8 ; extra == 'test'
